{
  "date": "2026-06-24",
  "entries": [
    {
      "docId": "S100YJ4U",
      "sec": "7864",
      "name": "株式会社フジシールインターナショナル",
      "desc": "臨時報告書",
      "issued": null,
      "remaining": null,
      "exercise_price": null,
      "expire": null,
      "per_right": null,
      "warrant": true
    },
    {
      "docId": "S100YIYL",
      "sec": "3132",
      "name": "マクニカホールディングス株式会社",
      "desc": "臨時報告書",
      "issued": null,
      "remaining": null,
      "exercise_price": null,
      "expire": null,
      "per_right": null,
      "warrant": true
    },
    {
      "docId": "S100YJD5",
      "sec": "5929",
      "name": "三和ホールディングス株式会社",
      "desc": "臨時報告書",
      "issued": null,
      "remaining": null,
      "exercise_price": null,
      "expire": null,
      "per_right": null,
      "warrant": true
    },
    {
      "docId": "S100YJ89",
      "sec": "7337",
      "name": "株式会社ひろぎんホールディングス",
      "desc": "臨時報告書",
      "issued": null,
      "remaining": null,
      "exercise_price": null,
      "expire": null,
      "per_right": null,
      "warrant": true
    },
    {
      "docId": "S100YIKE",
      "sec": "3946",
      "name": "株式会社トーモク",
      "desc": "臨時報告書",
      "issued": null,
      "remaining": null,
      "exercise_price": null,
      "expire": null,
      "per_right": null,
      "warrant": true
    },
    {
      "docId": "S100YJ5Q",
      "sec": "7167",
      "name": "株式会社めぶきフィナンシャルグループ",
      "desc": "臨時報告書",
      "issued": null,
      "remaining": null,
      "exercise_price": null,
      "expire": null,
      "per_right": null,
      "warrant": true
    },
    {
      "docId": "S100YIOY",
      "sec": "1961",
      "name": "三機工業株式会社",
      "desc": "臨時報告書",
      "issued": null,
      "remaining": null,
      "exercise_price": null,
      "expire": null,
      "per_right": null,
      "warrant": true
    },
    {
      "docId": "S100YIOJ",
      "sec": "6332",
      "name": "月島ホールディングス株式会社",
      "desc": "臨時報告書",
      "issued": null,
      "remaining": null,
      "exercise_price": null,
      "expire": null,
      "per_right": null,
      "warrant": true
    },
    {
      "docId": "S100YJ0U",
      "sec": "4005",
      "name": "住友化学株式会社",
      "desc": "臨時報告書",
      "issued": null,
      "remaining": null,
      "exercise_price": null,
      "expire": null,
      "per_right": null,
      "warrant": true
    },
    {
      "docId": "S100YH3Y",
      "sec": "8600",
      "name": "トモニホールディングス株式会社",
      "desc": "臨時報告書",
      "issued": null,
      "remaining": null,
      "exercise_price": null,
      "expire": null,
      "per_right": null,
      "warrant": true
    },
    {
      "docId": "S100YEI0",
      "sec": "8242",
      "name": "エイチ・ツー・オー　リテイリング株式会社",
      "desc": "臨時報告書",
      "issued": null,
      "remaining": null,
      "exercise_price": null,
      "expire": null,
      "per_right": null,
      "warrant": true
    },
    {
      "docId": "S100YJ4T",
      "sec": "6523",
      "name": "ＰＨＣホールディングス株式会社",
      "desc": "臨時報告書",
      "issued": null,
      "remaining": null,
      "exercise_price": null,
      "expire": null,
      "per_right": null,
      "warrant": true
    },
    {
      "docId": "S100YIZ0",
      "sec": "9987",
      "name": "株式会社スズケン",
      "desc": "臨時報告書",
      "issued": null,
      "remaining": null,
      "exercise_price": null,
      "expire": null,
      "per_right": null,
      "warrant": true
    },
    {
      "docId": "S100YIUS",
      "sec": "4819",
      "name": "株式会社デジタルガレージ",
      "desc": "臨時報告書",
      "issued": null,
      "remaining": null,
      "exercise_price": null,
      "expire": null,
      "per_right": null,
      "warrant": true
    },
    {
      "docId": "S100YFNL",
      "sec": "9984",
      "name": "ソフトバンクグループ株式会社",
      "desc": "臨時報告書",
      "issued": null,
      "remaining": 3754,
      "exercise_price": null,
      "expire": "2030年8月31日",
      "per_right": null,
      "warrant": true
    },
    {
      "docId": "S100YIVP",
      "sec": "8111",
      "name": "株式会社ゴールドウイン",
      "desc": "臨時報告書",
      "issued": null,
      "remaining": null,
      "exercise_price": null,
      "expire": null,
      "per_right": null,
      "warrant": true
    },
    {
      "docId": "S100YIUR",
      "sec": "4819",
      "name": "株式会社デジタルガレージ",
      "desc": "臨時報告書",
      "issued": null,
      "remaining": 113846,
      "exercise_price": null,
      "expire": "2076年7月10日",
      "per_right": null,
      "warrant": true
    },
    {
      "docId": "S100YIVB",
      "sec": "8056",
      "name": "ＢＩＰＲＯＧＹ株式会社",
      "desc": "臨時報告書",
      "issued": null,
      "remaining": null,
      "exercise_price": null,
      "expire": null,
      "per_right": null,
      "warrant": true
    },
    {
      "docId": "S100YISG",
      "sec": "6240",
      "name": "ヤマシンフィルタ株式会社",
      "desc": "臨時報告書",
      "issued": null,
      "remaining": null,
      "exercise_price": null,
      "expire": null,
      "per_right": null,
      "warrant": true
    },
    {
      "docId": "S100YJRW",
      "sec": "4507",
      "name": "塩野義製薬株式会社",
      "desc": "臨時報告書",
      "issued": null,
      "remaining": null,
      "exercise_price": null,
      "expire": null,
      "per_right": null,
      "warrant": true
    },
    {
      "docId": "S100YJRO",
      "sec": "7201",
      "name": "日産自動車株式会社",
      "desc": "臨時報告書",
      "issued": null,
      "remaining": null,
      "exercise_price": null,
      "expire": null,
      "per_right": null,
      "warrant": true
    },
    {
      "docId": "S100YJR5",
      "sec": "7995",
      "name": "株式会社バルカー",
      "desc": "臨時報告書",
      "issued": null,
      "remaining": null,
      "exercise_price": null,
      "expire": null,
      "per_right": null,
      "warrant": true
    },
    {
      "docId": "S100YHE6",
      "sec": "7013",
      "name": "株式会社ＩＨＩ",
      "desc": "臨時報告書",
      "issued": null,
      "remaining": null,
      "exercise_price": null,
      "expire": null,
      "per_right": null,
      "warrant": true
    },
    {
      "docId": "S100YJNK",
      "sec": "2871",
      "name": "株式会社ニチレイ",
      "desc": "臨時報告書",
      "issued": null,
      "remaining": null,
      "exercise_price": null,
      "expire": null,
      "per_right": null,
      "warrant": true
    },
    {
      "docId": "S100YIT3",
      "sec": "3679",
      "name": "株式会社じげん",
      "desc": "臨時報告書",
      "issued": 530000,
      "remaining": 5300,
      "exercise_price": 375,
      "expire": "2031年6月15日",
      "per_right": 100,
      "warrant": true
    },
    {
      "docId": "S100YJUT",
      "sec": "4183",
      "name": "三井化学株式会社",
      "desc": "臨時報告書",
      "issued": null,
      "remaining": null,
      "exercise_price": null,
      "expire": null,
      "per_right": null,
      "warrant": true
    },
    {
      "docId": "S100YJ6Y",
      "sec": "7173",
      "name": "株式会社東京きらぼしフィナンシャルグループ",
      "desc": "臨時報告書",
      "issued": null,
      "remaining": null,
      "exercise_price": null,
      "expire": null,
      "per_right": null,
      "warrant": true
    },
    {
      "docId": "S100YJW5",
      "sec": "9684",
      "name": "株式会社スクウェア・エニックス・ホールディングス",
      "desc": "臨時報告書",
      "issued": null,
      "remaining": null,
      "exercise_price": null,
      "expire": null,
      "per_right": null,
      "warrant": true
    },
    {
      "docId": "S100YJWH",
      "sec": "4973",
      "name": "日本高純度化学株式会社",
      "desc": "臨時報告書",
      "issued": null,
      "remaining": 186,
      "exercise_price": null,
      "expire": "2031年6月30日",
      "per_right": null,
      "warrant": true
    },
    {
      "docId": "S100YJYG",
      "sec": "7199",
      "name": "プレミアグループ株式会社",
      "desc": "臨時報告書",
      "issued": null,
      "remaining": null,
      "exercise_price": null,
      "expire": null,
      "per_right": null,
      "warrant": true
    },
    {
      "docId": "S100YJ2B",
      "sec": "6963",
      "name": "ローム株式会社",
      "desc": "臨時報告書",
      "issued": null,
      "remaining": null,
      "exercise_price": null,
      "expire": null,
      "per_right": null,
      "warrant": true
    },
    {
      "docId": "S100YK0A",
      "sec": "8844",
      "name": "株式会社コスモスイニシア",
      "desc": "臨時報告書",
      "issued": null,
      "remaining": null,
      "exercise_price": null,
      "expire": null,
      "per_right": null,
      "warrant": true
    }
  ]
}